adminsortable2/__init__.py
adminsortable2/admin.py
adminsortable2/models.py
adminsortable2/locale/de/LC_MESSAGES/django.mo
adminsortable2/locale/de/LC_MESSAGES/django.po
adminsortable2/locale/en/LC_MESSAGES/django.mo
adminsortable2/locale/en/LC_MESSAGES/django.po
adminsortable2/locale/es/LC_MESSAGES/django.mo
adminsortable2/locale/es/LC_MESSAGES/django.po
adminsortable2/locale/fa/LC_MESSAGES/django.mo
adminsortable2/locale/fa/LC_MESSAGES/django.po
adminsortable2/locale/fr/LC_MESSAGES/django.mo
adminsortable2/locale/fr/LC_MESSAGES/django.po
adminsortable2/locale/it/LC_MESSAGES/django.mo
adminsortable2/locale/it/LC_MESSAGES/django.po
adminsortable2/locale/pl/LC_MESSAGES/django.mo
adminsortable2/locale/pl/LC_MESSAGES/django.po
adminsortable2/locale/ru/LC_MESSAGES/django.mo
adminsortable2/locale/ru/LC_MESSAGES/django.po
adminsortable2/locale/uk/LC_MESSAGES/django.mo
adminsortable2/locale/uk/LC_MESSAGES/django.po
adminsortable2/management/__init__.py
adminsortable2/management/commands/__init__.py
adminsortable2/management/commands/reorder.py
adminsortable2/static/adminsortable2/css/sortable.css
adminsortable2/static/adminsortable2/icons/drag.png
adminsortable2/static/adminsortable2/js/adminsortable2.js
adminsortable2/static/adminsortable2/js/adminsortable2.min.js
adminsortable2/templates/adminsortable2/change_list.html
adminsortable2/templates/adminsortable2/edit_inline/stacked-django-4.2.html
adminsortable2/templates/adminsortable2/edit_inline/stacked-django-5.0.html
adminsortable2/templates/adminsortable2/edit_inline/stacked-django-5.1.html
adminsortable2/templates/adminsortable2/edit_inline/stacked-django-5.1.html.orig
adminsortable2/templates/adminsortable2/edit_inline/stacked-django-5.2.html
adminsortable2/templates/adminsortable2/edit_inline/stacked-django-5.2.html.orig
adminsortable2/templates/adminsortable2/edit_inline/tabular-django-4.2.html
adminsortable2/templates/adminsortable2/edit_inline/tabular-django-4.2.html.orig
django_admin_sortable2-2.2.7.dist-info/licenses/LICENSE
django_admin_sortable2-2.2.7.dist-info/METADATA
django_admin_sortable2-2.2.7.dist-info/WHEEL
django_admin_sortable2-2.2.7.dist-info/top_level.txt
django_admin_sortable2-2.2.7.dist-info/RECORD
